stinky/__init__.py
stinky/noodle/__init__.py
stinky/noodle/core.py
stinky/noodle/utils/__init__.py
stinky/noodle/utils/builtins.py
stinky/noodle/utils/enforcer.py
stinky/noodle/utils/exceptions.py
stinky/noodle/utils/parser.py
stinky/noodle/utils/ruleset.py
stinky_noodle-0.0.10.dist-info/METADATA
stinky_noodle-0.0.10.dist-info/WHEEL
stinky_noodle-0.0.10.dist-info/entry_points.txt
stinky_noodle-0.0.10.dist-info/top_level.txt
stinky_noodle-0.0.10.dist-info/RECORD
