Metadata-Version: 2.1
Name: stinky-noodle
Version: 0.0.10
Summary: Stinky noodle is a Python-based OpenAPI spec linter compatible with spectral rulesets
Author-email: Riccardo Tiebax <riccardo.t@gmail.com>
Requires-Dist: convert-case ==1.2.3
Requires-Dist: jsonschema ==4.21.1
Requires-Dist: loguru ==0.7.2
Requires-Dist: pydantic ==2.6.4
Requires-Dist: pyjsonpath ==1.2.3
Provides-Extra: tests
